dadosbrasil/__init__.py
dadosbrasil/dados.py
testingvaleria-1.0.4.dist-info/LICENSE
testingvaleria-1.0.4.dist-info/METADATA
testingvaleria-1.0.4.dist-info/WHEEL
testingvaleria-1.0.4.dist-info/top_level.txt
testingvaleria-1.0.4.dist-info/RECORD
