Metadata-Version: 2.1
Name: testingvaleria
Version: 1.0.4
Summary: Uma biblioteca para análise de investimentos
Home-page: https://github.com/testevaleria/valeriatesting
Author: Valeriateste
Author-email: valeria.souzadsantos@gmail.com
License: MIT
Platform: UNKNOWN
License-File: LICENSE
